spotify_dlp/__init__.py
spotify_dlp/__main__.py
spotify_dlp/spotify_api.py
spotify_dlp/spotify_dlp.py
spotify_dlp/utils.py
spotify_dlp-2.6.0.dist-info/licenses/LICENSE
spotify_dlp-2.6.0.dist-info/METADATA
spotify_dlp-2.6.0.dist-info/WHEEL
spotify_dlp-2.6.0.dist-info/entry_points.txt
spotify_dlp-2.6.0.dist-info/top_level.txt
spotify_dlp-2.6.0.dist-info/RECORD
