Metadata-Version: 2.4
Name: spotify-dlp
Version: 2.6.0
Summary: Command line downloader for spotify tracks, playlists, albums and top artists songs.
Home-page: https://github.com/zWolfrost/spotify-dlp
Author: zWolfrost
License-File: LICENSE
Requires-Dist: requests>=2.31.0
Requires-Dist: yt_dlp>=2024.4.9
Dynamic: author
Dynamic: description
Dynamic: description-content-type
Dynamic: home-page
Dynamic: license-file
Dynamic: requires-dist
Dynamic: summary
